sentry_check.py
sentry_flake8-2.0.0.dist-info/LICENSE
sentry_flake8-2.0.0.dist-info/METADATA
sentry_flake8-2.0.0.dist-info/WHEEL
sentry_flake8-2.0.0.dist-info/entry_points.txt
sentry_flake8-2.0.0.dist-info/top_level.txt
sentry_flake8-2.0.0.dist-info/RECORD
